{
    "boxShadow": "none",
    "widgetName": "create_customer_heading",
    "borderColor": "#FFFFFF",
    "isCanvas": true,
    "dynamicPropertyPathList": [{"key": "borderRadius"}],
    "displayName": "Container",
    "iconSVG": "/static/media/icon.1977dca3.svg",
    "topRow": 0,
    "bottomRow": 6,
    "parentRowSpace": 10,
    "type": "CONTAINER_WIDGET",
    "hideCard": false,
    "animateLoading": true,
    "parentColumnSpace": 18.0625,
    "dynamicTriggerPathList": [],
    "leftColumn": 0,
    "dynamicBindingPathList": [],
    "children": [{
        "boxShadow": "none",
        "widgetName": "Canvas110",
        "displayName": "Canvas",
        "topRow": 0,
        "bottomRow": 60,
        "parentRowSpace": 1,
        "type": "CANVAS_WIDGET",
        "canExtend": false,
        "hideCard": true,
        "minHeight": 400,
        "parentColumnSpace": 1,
        "leftColumn": 0,
        "dynamicBindingPathList": [],
        "key": "ffadum178l",
        "labelTextSize": "0.875rem",
        "rightColumn": 433.5,
        "detachFromLayout": true,
        "widgetId": "1izq31lr7q",
        "containerStyle": "none",
        "isVisible": true,
        "version": 1,
        "parentId": "oae8y9jv4w",
        "renderMode": "CANVAS",
        "isLoading": false,
        "borderRadius": "0px"
    }],
    "borderWidth": "0",
    "key": "6bzu8mpizb",
    "labelTextSize": "0.875rem",
    "backgroundColor": "#f4f4f5",
    "rightColumn": 63,
    "dynamicHeight": "FIXED",
    "widgetId": "oae8y9jv4w",
    "containerStyle": "card",
    "isVisible": true,
    "version": 1,
    "parentId": "92p4tr4iac",
    "renderMode": "CANVAS",
    "isLoading": false,
    "borderRadius": "5px",
    "maxDynamicHeight": 9000,
    "minDynamicHeight": 4
}