{
    "boxShadow": "none",
    "isVisibleDownload": false,
    "iconSVG": "/static/media/icon.db8a9cbd.svg",
    "topRow": 4,
    "isSortable": true,
    "onPageChange": "{{getDelegationList.run(() => {}, () => common_utils.error401())}}",
    "type": "TABLE_WIDGET",
    "animateLoading": true,
    "dynamicBindingPathList": [
        {"key": "tableData"},
        {"key": "accentColor"},
        {"key": "primaryColumns.request_id.computedValue"},
        {"key": "primaryColumns.company_name.computedValue"},
        {"key": "primaryColumns.username.computedValue"},
        {"key": "primaryColumns.creation_time.computedValue"},
        {"key": "primaryColumns.expiry_time.computedValue"},
        {"key": "primaryColumns.account_id.computedValue"},
        {"key": "derivedColumns.customColumn1.buttonColor"},
        {"key": "primaryColumns.customColumn1.buttonColor"},
        {"key": "derivedColumns.customColumn1.borderRadius"},
        {"key": "derivedColumns.customColumn1.boxShadow"},
        {"key": "primaryColumns.customColumn1.boxShadow"},
        {"key": "derivedColumns.customColumn1.buttonLabel"},
        {"key": "primaryColumns.customColumn1.buttonLabel"},
        {"key": "primaryColumns.customColumn1.borderRadius"},
        {"key": "derivedColumns.customColumn1.isCellVisible"},
        {"key": "primaryColumns.customColumn1.isCellVisible"},
        {"key": "isVisible"}
    ],
    "leftColumn": 0,
    "delimiter": ",",
    "accentColor": "{{appsmith.theme.colors.primaryColor}}",
    "isVisibleFilters": false,
    "isVisible": "{{customer_list.delegationShow()}}",
    "enableClientSideSearch": true,
    "version": 3,
    "textColor": "#2E3D49",
    "totalRecordsCount": "",
    "isLoading": false,
    "onSearchTextChanged": "",
    "childStylesheet": {
        "button": {
            "boxShadow": "none",
            "borderRadius": "{{appsmith.theme.borderRadius.appBorderRadius}}",
            "buttonColor": "{{appsmith.theme.colors.primaryColor}}"
        },
        "iconButton": {
            "boxShadow": "none",
            "borderRadius": "{{appsmith.theme.borderRadius.appBorderRadius}}",
            "menuColor": "{{appsmith.theme.colors.primaryColor}}"
        },
        "menuButton": {
            "boxShadow": "none",
            "borderRadius": "{{appsmith.theme.borderRadius.appBorderRadius}}",
            "menuColor": "{{appsmith.theme.colors.primaryColor}}"
        }
    },
    "borderRadius": "0px",
    "primaryColumnId": "company_display_name",
    "columnSizeMap": {
        "creation_time": 215,
        "account_type": 123,
        "company_display_name": 148,
        "data_center": 177,
        "customColumn1": 109,
        "last_run": 94,
        "customColumn2": 135,
        "duration": 171,
        "task": 245,
        "job_name": 226,
        "next_run": 173,
        "subdomain": 291,
        "step": 62,
        "expiry_time": 253,
        "status": 80,
        "username": 227
    },
    "widgetName": "delegation_list_table",
    "defaultPageSize": 0,
    "columnOrder": [
        "company_name",
        "username",
        "creation_time",
        "expiry_time",
        "request_id",
        "account_id",
        "customColumn1"
    ],
    "dynamicPropertyPathList": [
        {"key": "primaryColumns.customColumn1.borderRadius"},
        {"key": "primaryColumns.customColumn1.onClick"},
        {"key": "primaryColumns.customColumn1.isCellVisible"},
        {"key": "isVisible"}
    ],
    "displayName": "Table",
    "bottomRow": 55,
    "parentRowSpace": 10,
    "defaultSelectedRow": "",
    "hideCard": false,
    "parentColumnSpace": 18.0625,
    "dynamicTriggerPathList": [
        {"key": "onPageChange"},
        {"key": "onSearchTextChanged"},
        {"key": "primaryColumns.customColumn1.onClick"}
    ],
    "primaryColumns": {
        "creation_time": {
            "isCellVisible": true,
            "isDerived": false,
            "computedValue": "{{delegation_list_table.sanitizedTableData.map((currentRow) => ( currentRow.creation_time))}}",
            "textSize": "0.875rem",
            "iconName": "",
            "index": 3,
            "isVisible": true,
            "label": "Creation Time",
            "inputFormat": "YYYY-MM-DDTHH:mm:ss.SSSZ",
            "textColor": "#2E3D49",
            "columnType": "date",
            "horizontalAlignment": "LEFT",
            "width": 150,
            "enableFilter": true,
            "enableSort": true,
            "id": "creation_time",
            "isDisabled": false,
            "cellBackground": "#FFFFFF",
            "outputFormat": "H:mm A D MMMM, YYYY",
            "verticalAlignment": "CENTER"
        },
        "account_id": {
            "isCellVisible": true,
            "isDerived": false,
            "computedValue": "{{delegation_list_table.sanitizedTableData.map((currentRow) => ( currentRow.account_id))}}",
            "textSize": "0.875rem",
            "index": 5,
            "isVisible": false,
            "label": "account_id",
            "textColor": "#2E3D49",
            "columnType": "text",
            "horizontalAlignment": "LEFT",
            "width": 150,
            "enableFilter": true,
            "enableSort": true,
            "id": "account_id",
            "isDisabled": false,
            "cellBackground": "#FFFFFF",
            "verticalAlignment": "CENTER"
        },
        "company_name": {
            "isCellVisible": true,
            "isDerived": false,
            "computedValue": "{{delegation_list_table.sanitizedTableData.map((currentRow) => ( currentRow.company_name))}}",
            "textSize": "0.875rem",
            "index": 1,
            "isVisible": false,
            "label": "company_name",
            "textColor": "#2E3D49",
            "columnType": "text",
            "horizontalAlignment": "LEFT",
            "width": 150,
            "enableFilter": true,
            "enableSort": true,
            "id": "company_name",
            "isDisabled": false,
            "cellBackground": "#FFFFFF",
            "verticalAlignment": "CENTER"
        },
        "customColumn1": {
            "isCellVisible": "{{delegation_list_table.sanitizedTableData.map((currentRow) => ( common_utils.matchPermission(['login_as_tenant_user'])))}}",
            "boxShadow": "{{delegation_list_table.sanitizedTableData.map((currentRow) => ( 'none'))}}",
            "isDerived": true,
            "computedValue": "",
            "onClick": "{{customer_list.getCustomerUrl(currentRow.account_id,currentRow.request_id)}}",
            "buttonColor": "{{delegation_list_table.sanitizedTableData.map((currentRow) => ( appsmith.theme.colors.primaryColor))}}",
            "iconName": "",
            "buttonStyle": "rgb(3, 179, 101)",
            "index": 6,
            "isVisible": true,
            "label": "Action",
            "labelColor": "#FFFFFF",
            "buttonLabel": "{{delegation_list_table.sanitizedTableData.map((currentRow) => ( 'Login As'))}}",
            "columnType": "button",
            "borderRadius": "{{delegation_list_table.sanitizedTableData.map((currentRow) => ( '5'))}}",
            "buttonVariant": "SECONDARY",
            "width": 150,
            "enableFilter": true,
            "enableSort": true,
            "id": "customColumn1",
            "isDisabled": false
        },
        "expiry_time": {
            "isCellVisible": true,
            "isDerived": false,
            "computedValue": "{{delegation_list_table.sanitizedTableData.map((currentRow) => ( currentRow.expiry_time))}}",
            "textSize": "0.875rem",
            "iconName": "",
            "index": 4,
            "isVisible": true,
            "label": "Expiry Time",
            "inputFormat": "YYYY-MM-DDTHH:mm:ss.SSSZ",
            "textColor": "#2E3D49",
            "columnType": "date",
            "horizontalAlignment": "LEFT",
            "width": 150,
            "enableFilter": true,
            "enableSort": true,
            "id": "expiry_time",
            "isDisabled": false,
            "cellBackground": "#FFFFFF",
            "outputFormat": "H:mm A D MMMM, YYYY",
            "verticalAlignment": "CENTER"
        },
        "request_id": {
            "isCellVisible": true,
            "isDerived": false,
            "computedValue": "{{delegation_list_table.sanitizedTableData.map((currentRow) => ( currentRow.request_id))}}",
            "textSize": "0.875rem",
            "index": 0,
            "isVisible": false,
            "label": "request_id",
            "textColor": "#2E3D49",
            "columnType": "text",
            "horizontalAlignment": "LEFT",
            "width": 150,
            "enableFilter": true,
            "enableSort": true,
            "id": "request_id",
            "isDisabled": false,
            "cellBackground": "#FFFFFF",
            "verticalAlignment": "CENTER"
        },
        "username": {
            "isCellVisible": true,
            "isDerived": false,
            "computedValue": "{{delegation_list_table.sanitizedTableData.map((currentRow) => ( currentRow.username))}}",
            "textSize": "0.875rem",
            "index": 2,
            "isVisible": true,
            "label": "username",
            "textColor": "#2E3D49",
            "columnType": "text",
            "horizontalAlignment": "LEFT",
            "width": 150,
            "enableFilter": true,
            "enableSort": true,
            "id": "username",
            "isDisabled": false,
            "cellBackground": "#FFFFFF",
            "verticalAlignment": "CENTER"
        }
    },
    "key": "u3vtezv7sn",
    "derivedColumns": {"customColumn1": {
        "isCellVisible": "{{delegation_list_table.sanitizedTableData.map((currentRow) => ( common_utils.matchPermission(['login_as_tenant_user'])))}}",
        "boxShadow": "{{delegation_list_table.sanitizedTableData.map((currentRow) => ( 'none'))}}",
        "isDerived": true,
        "computedValue": "",
        "buttonColor": "{{delegation_list_table.sanitizedTableData.map((currentRow) => ( appsmith.theme.colors.primaryColor))}}",
        "iconName": "",
        "buttonStyle": "rgb(3, 179, 101)",
        "index": 6,
        "isVisible": true,
        "label": "Action",
        "labelColor": "#FFFFFF",
        "buttonLabel": "{{delegation_list_table.sanitizedTableData.map((currentRow) => ( 'Login As'))}}",
        "columnType": "button",
        "borderRadius": "{{delegation_list_table.sanitizedTableData.map((currentRow) => ( '5'))}}",
        "buttonVariant": "SECONDARY",
        "width": 150,
        "enableFilter": true,
        "enableSort": true,
        "id": "customColumn1",
        "isDisabled": false
    }},
    "labelTextSize": "0.875rem",
    "rightColumn": 64,
    "textSize": "0.875rem",
    "widgetId": "fzlqphypj6",
    "tableData": "{{getDelegationList.data.filter((item)=>{ return item.account_id === customer_list_table.selectedRow.CustomerID})}}",
    "label": "Data",
    "searchKey": "",
    "parentId": "sz2slgaua3",
    "serverSidePaginationEnabled": false,
    "renderMode": "CANVAS",
    "horizontalAlignment": "LEFT",
    "isVisibleSearch": false,
    "isVisiblePagination": false,
    "iconAlign": "left",
    "cellBackground": "#FFFFFF",
    "verticalAlignment": "CENTER"
}